mox_helpers/__init__.py
mox_helpers/mox_helper.py
mox_helpers/mox_util.py
mox_helpers/payloads.py
mox_helpers/requirements.txt
mox_helpers/utils.py
os2mo_data_import/__init__.py
os2mo_data_import/caching_import.py
os2mo_data_import/defaults.py
os2mo_data_import/helpers.py
os2mo_data_import/mora_data_types.py
os2mo_data_import/mox_data_types.py
os2mo_data_import/tests/__init__.py
os2mo_data_import/tests/test_utilities.py
os2mo_data_import/utilities.py
os2mo_helpers/__init__.py
os2mo_helpers/mora_helpers.py
os2mo_helpers/requirements.txt
os2mo_helpers/settings.py
os2mo_helpers/tests/__init__.py
os2mo_helpers/tests/test_morahelpers.py
os2mo_data_import-6.2.4.dist-info/METADATA
os2mo_data_import-6.2.4.dist-info/WHEEL
os2mo_data_import-6.2.4.dist-info/licenses/LICENSES/MPL-2.0.txt
os2mo_data_import-6.2.4.dist-info/RECORD
