Metadata-Version: 2.4
Name: os2mo_data_import
Version: 6.2.4
Summary: A set of tools for OS2MO data import and export
License: MPL-2.0
License-File: LICENSES/MPL-2.0.txt
Keywords: os2mo,dipex
Author: Magenta
Author-email: info@magenta.dk
Requires-Python: >=3.11,<4.0
Classifier: License :: OSI Approved
Classifier: Programming Language :: Python :: 3
Classifier: Programming Language :: Python :: 3.11
Classifier: Programming Language :: Python :: 3.12
Classifier: Programming Language :: Python :: 3.13
Classifier: Programming Language :: Python :: 3.14
Requires-Dist: XlsxWriter (>=3.0.9,<4.0.0)
Requires-Dist: aiohttp (>=3.8.4,<4.0.0)
Requires-Dist: anytree (>=2.8.0,<3.0.0)
Requires-Dist: chardet (>=5.1.0,<6.0.0)
Requires-Dist: click (>=8.1.3,<9.0.0)
Requires-Dist: fastramqpi (>=5.7)
Requires-Dist: idna (>=3.4,<4.0)
Requires-Dist: jsonschema (>=4.17.3,<5.0.0)
Requires-Dist: more-itertools (>=9.1.0,<10.0.0)
Requires-Dist: openpyxl (>=3.1.2,<4.0.0)
Requires-Dist: pydantic (>=1.10.7,<2.0.0)
Requires-Dist: requests (>=2.28.2,<3.0.0)
Requires-Dist: tenacity (>=8.2.2,<9.0.0)
Requires-Dist: xmltodict (>=0.13.0,<0.14.0)
Project-URL: Repository, https://git.magenta.dk/rammearkitektur/os2mo_data_import
